pinpong/__init__.py
pinpong/board.py
pinpong/base/DfuUtil.py
pinpong/base/EspTool.py
pinpong/base/FirmataExpress.HANDPY.2.9.bin
pinpong/base/FirmataExpress.LEONARDO.2.7.hex
pinpong/base/FirmataExpress.MEGA2560.2.8.hex
pinpong/base/FirmataExpress.MICROBIT.2.9.hex
pinpong/base/FirmataExpress.MICROBITV2.2.9.hex
pinpong/base/FirmataExpress.UNIHIKER.3.7.bin
pinpong/base/FirmataExpress.UNIHIKER.3.8.bin
pinpong/base/FirmataExpress.UNO.2.8.hex
pinpong/base/FirmataExpress.UNO_PB.2.7.hex
pinpong/base/__init__.py
pinpong/base/avrdude.conf
pinpong/base/avrdude.py
pinpong/base/boot_app0.bin
pinpong/base/bootloader_dio_80m.bin
pinpong/base/butterfly.py
pinpong/base/butterfly_param.py
pinpong/base/comm.py
pinpong/base/dfrobot.ino.partitions.bin
pinpong/base/help.py
pinpong/base/i2c.py
pinpong/base/microbit.py
pinpong/base/msyh.ttf
pinpong/base/pin_data.py
pinpong/base/private_constants.py
pinpong/base/programmer.py
pinpong/base/pymata4.py
pinpong/base/stk500.py
pinpong/base/stk500_param.py
pinpong/base/stk500v2.py
pinpong/base/stk500v2_param.py
pinpong/examples/1-01-blink.py
pinpong/examples/1-02-button.py
pinpong/examples/1-03-adc.py
pinpong/examples/1-04-pwm.py
pinpong/examples/1-05-irq.py
pinpong/examples/10-01-ens160.py
pinpong/examples/11-01-iic_to_serial.py
pinpong/examples/11-02-windspeed_uart_i2c.py
pinpong/examples/11-03-winddirection_uart_i2c.py
pinpong/examples/11-04-mics_get_gas_ppm.py
pinpong/examples/11-05-mics_get_gas_exist.py
pinpong/examples/11-06-mics_get_adc_data.py
pinpong/examples/11-07-mics_enable_power.py
pinpong/examples/12-01-ph.py
pinpong/examples/12-02-ph2.py
pinpong/examples/12-03-max30102_get_data.py
pinpong/examples/12-04-speech_synthesis.py
pinpong/examples/12-05-gravityPM25.py
pinpong/examples/12-06-asr.py
pinpong/examples/2-01-tone.py
pinpong/examples/2-02-servo.py
pinpong/examples/2-03-sr04_urm10.py
pinpong/examples/2-04-dht.py
pinpong/examples/2-05-lcd1602.py
pinpong/examples/2-06-oled12864.py
pinpong/examples/2-07-neopixel.py
pinpong-0.5.2.dist-info/METADATA
pinpong-0.5.2.dist-info/WHEEL
pinpong-0.5.2.dist-info/entry_points.txt
pinpong-0.5.2.dist-info/license.txt
pinpong-0.5.2.dist-info/top_level.txt
pinpong-0.5.2.dist-info/RECORD
